{
  "accrualStartDateByYear" : {

  },
  "bancaOreInizialeHours" : 0,
  "bancaOreInizialeMinutesPart" : 0,
  "decurtazioniBancaOreByMonth" : {

  },
  "defaultDailyWorkMinutes" : 462,
  "ferieTotaliByYear" : {
    "2025" : 20,
    "2026" : 26
  },
  "festivitaTotaliByYear" : {
    "2025" : 0,
    "2026" : 4
  },
  "mezziByDate" : {

  },
  "noteByDate" : {

  },
  "riposiCompensativiByDate" : {

  },
  "sigleByDate" : {
    "2026-04-08" : "p",
    "2026-04-09" : "p",
    "2026-04-10" : "p",
    "2026-04-13" : "p",
    "2026-04-14" : "p",
    "2026-04-15" : "p",
    "2026-04-16" : "p",
    "2026-04-17" : "p",
    "2026-04-20" : "p",
    "2026-04-21" : "p",
    "2026-04-22" : "p",
    "2026-04-23" : "p",
    "2026-04-24" : "p",
    "2026-04-27" : "p",
    "2026-04-28" : "p",
    "2026-04-29" : "p",
    "2026-04-30" : "p",
    "2026-05-04" : "p"
  },
  "smartWorkingMonthlyTarget" : 10,
  "standardWorkMinutesByDate" : {

  },
  "workScheduleByDay" : {

  }
}
